setup.py
wenyali/__init__.py
wenyali/index.py
wenyali_console.egg-info/PKG-INFO
wenyali_console.egg-info/SOURCES.txt
wenyali_console.egg-info/dependency_links.txt
wenyali_console.egg-info/entry_points.txt
wenyali_console.egg-info/top_level.txt
wenyali_console.egg-info/zip-safe
wyl/__init__.py
wyl/first.py