Metadata-Version: 1.1
Name: wenyali-console
Version: 1.1.2
Summary: this is a test package for return hello world
Home-page: https://github.com/lichanghong/wenyali.git
Author: wenyali
Author-email: 2917073217@qq.com
License: UNKNOWN
Keywords: hello world
Platform: UNKNOWN
Classifier: License :: OSI Approved :: MIT License
Classifier: Programming Language :: Python
Classifier: Intended Audience :: Developers
Classifier: Operating System :: OS Independent
